[
  {
    "fullName": "Elon Musk",
    "contact": [
      "elon@tesla.com",
      "Austin, Texas",
      "+1-555-0123"
    ],
    "id": 1
  },
  {
    "fullName": "Bill Gates",
    "contact": [
      "bill@microsoft.com",
      "Seattle, Washington",
      "+1-555-0124"
    ],
    "id": 2
  },
  {
    "fullName": "Mark Zuckerberg",
    "contact": [
      "mark@meta.com",
      "Palo Alto, California",
      "+1-555-0125"
    ],
    "id": 3
  },
  {
    "fullName": "Jeff Bezos",
    "contact": [
      "jeff@amazon.com",
      "Seattle, Washington",
      "+1-555-0126"
    ],
    "id": 4
  },
  {
    "fullName": "Tim Cook",
    "contact": [
      "tim@apple.com",
      "Cupertino, California",
      "+1-555-0127"
    ],
    "id": 5
  },
  {
    "fullName": "Satya Nadella",
    "contact": [
      "satya@microsoft.com",
      "Redmond, Washington",
      "+1-555-0128"
    ],
    "id": 6
  },
  {
    "fullName": "Sundar Pichai",
    "contact": [
      "sundar@google.com",
      "Mountain View, California",
      "+1-555-0129"
    ],
    "id": 7
  },
  {
    "fullName": "Jensen Huang",
    "contact": [
      "jensen@nvidia.com",
      "Santa Clara, California",
      "+1-555-0130"
    ],
    "id": 8
  },
  {
    "fullName": "Reed Hastings",
    "contact": [
      "reed@netflix.com",
      "Los Gatos, California",
      "+1-555-0131"
    ],
    "id": 9
  },
  {
    "fullName": "Andy Jassy",
    "contact": [
      "andy@amazon.com",
      "Seattle, Washington",
      "+1-555-0132"
    ],
    "id": 10
  },
  {
    "fullName": "phu",
    "contact": [
      "phuhk9@gmsd.com",
      "viet nam",
      "02232323232"
    ],
    "id": 11
  }
]